[
  {
    "adult": false,
    "backdrop_path": "/70nxSw3mFBsGmtkvcs91PbjerwD.jpg",
    "genre_ids": [878, 28, 12],
    "id": 580489,
    "original_language": "en",
    "original_title": "Venom: Let There Be Carnage",
    "overview": "Em busca de seu próximo furo de reportagem, o jornalista Eddie Brock consegue uma entrevista exclusiva com Cletus Kasady, um assassino no corredor da morte, que descobre o segredo de Eddie e se torna o hospedeiro de Carnificina, um simbionte aterrorizante e ameaçador. Eddie e Venom precisam superar sua relação atribulada e trabalhar em conjunto para derrotar Carnificina.",
    "popularity": 8633.976,
    "poster_path": "/h5UzYZquMwO9FVn15R2eK2itmHu.jpg",
    "release_date": "2021-09-30",
    "title": "Venom: Tempo de Carnificina",
    "video": false,
    "vote_average": 7.2,
    "vote_count": 4398
  },
  {
    "adult": false,
    "backdrop_path": "/dK12GIdhGP6NPGFssK2Fh265jyr.jpg",
    "genre_ids": [28, 35, 80, 53],
    "id": 512195,
    "original_language": "en",
    "original_title": "Red Notice",
    "overview": "No mundo do crime internacional, a INTERPOL lança um Alerta Vermelho, o que inicia uma caçada para capturar a mais notória ladra de artes do globo.",
    "popularity": 4825.133,
    "poster_path": "/pe17f8VDfzbvbHSAKAlcORtBHmW.jpg",
    "release_date": "2021-11-04",
    "title": "Alerta Vermelho",
    "video": false,
    "vote_average": 6.8,
    "vote_count": 1970
  },
  {
    "adult": false,
    "backdrop_path": "/zBkHCpLmHjW2uVURs5uZkaVmgKR.jpg",
    "genre_ids": [16, 35, 10751],
    "id": 585245,
    "original_language": "en",
    "original_title": "Clifford the Big Red Dog",
    "overview": "Clifford era um pequeno filhotinho de cachorro vermelho que vivia em uma casa repleta de amor e cuidado. Porém, o amor de sua jovem dona, Emily Elizabeth, por ele é tão grande, que o cão cresce até atingir um tamanho gigantesco.",
    "popularity": 3280.16,
    "poster_path": "/s7Cn3OsY32tH5cyz7CHxYdEiXMn.jpg",
    "release_date": "2021-11-10",
    "title": "Clifford, o Gigante Cão Vermelho",
    "video": false,
    "vote_average": 7.5,
    "vote_count": 530
  },
  {
    "adult": false,
    "backdrop_path": "/mFbS5TwN95BcSEfiztdchLgTQ0v.jpg",
    "genre_ids": [28, 18, 36],
    "id": 617653,
    "original_language": "en",
    "original_title": "The Last Duel",
    "overview": "História sobre o duelo entre o cavaleiro Jean de Carrouges e o escudeiro Jaques Le Gris, acusado de ter violado a esposa do cavaleiro. A luta, estabelecida pelo próprio rei da França, Carlos VI, marca o grande drama de vingança e crime do século XIV, que tem a esperança de ser resolvido somente após o combate.",
    "popularity": 3256.364,
    "poster_path": "/mhrzzNauB1PKrwnqVbLQODNNTJN.jpg",
    "release_date": "2021-10-13",
    "title": "O Último Duelo",
    "video": false,
    "vote_average": 7.6,
    "vote_count": 870
  },
  {
    "adult": false,
    "backdrop_path": "/cinER0ESG0eJ49kXlExM0MEWGxW.jpg",
    "genre_ids": [28, 12, 14],
    "id": 566525,
    "original_language": "en",
    "original_title": "Shang-Chi and the Legend of the Ten Rings",
    "overview": "Shang-Chi precisa confrontar o passado que pensou ter deixado para trás. Ao mesmo tempo, ele é envolvido em uma teia de mistérios da organização conhecida como Dez Anéis.",
    "popularity": 3189.442,
    "poster_path": "/ArrOBeio968bUuUOtEpKa1teIh4.jpg",
    "release_date": "2021-09-01",
    "title": "Shang-Chi e a Lenda dos Dez Anéis",
    "video": false,
    "vote_average": 7.8,
    "vote_count": 4201
  },
  {
    "adult": false,
    "backdrop_path": "/5RuR7GhOI5fElADXZb0X2sr9w5n.jpg",
    "genre_ids": [16, 35, 10751, 14, 10402],
    "id": 568124,
    "original_language": "en",
    "original_title": "Encanto",
    "overview": "Uma garota chamada Mirabel Madrigal cresce como o único membro não mágico de sua família, que vivem escondidos em uma vibrante casa encantada nas montanhas da Colômbia.",
    "popularity": 2989.673,
    "poster_path": "/4j0PNHkMr5ax3IA8tjtxcmPU3QT.jpg",
    "release_date": "2021-11-24",
    "title": "Encanto",
    "video": false,
    "vote_average": 7.4,
    "vote_count": 307
  }
]
